{
  "id": "hero",
  "type": "SharedSlice",
  "name": "Hero",
  "description": "Hero",
  "variations": [
    {
      "id": "default",
      "name": "Default",
      "docURL": "...",
      "version": "initial",
      "description": "Default",
      "imageUrl": "",
      "primary": {
        "title": {
          "type": "Text",
          "config": {
            "label": "title",
            "placeholder": ""
          }
        },
        "subtitle": {
          "type": "StructuredText",
          "config": {
            "label": "subtitle",
            "placeholder": "",
            "allowTargetBlank": true,
            "multi": "paragraph,preformatted,heading1,heading2,heading3,heading4,heading5,heading6,strong,em,hyperlink,image,embed,list-item,o-list-item,rtl"
          }
        },
        "image": {
          "type": "Image",
          "config": {
            "label": "image",
            "constraint": {},
            "thumbnails": []
          }
        },
        "button": {
          "type": "Link",
          "config": {
            "label": "button",
            "placeholder": "",
            "select": null,
            "allowTargetBlank": true,
            "allowText": true,
            "repeat": false
          }
        }
      },
      "items": {}
    },
    {
      "id": "slider",
      "name": "slider",
      "docURL": "...",
      "version": "initial",
      "description": "Default",
      "imageUrl": "",
      "primary": {
        "title": {
          "type": "Text",
          "config": {
            "label": "title",
            "placeholder": ""
          }
        },
        "subtitle": {
          "type": "StructuredText",
          "config": {
            "label": "subtitle",
            "placeholder": "",
            "allowTargetBlank": true,
            "multi": "paragraph,preformatted,heading1,heading2,heading3,heading4,heading5,heading6,strong,em,hyperlink,image,embed,list-item,o-list-item,rtl"
          }
        },
        "images": {
          "type": "Group",
          "config": {
            "label": "images",
            "repeat": true,
            "fields": {
              "image": {
                "type": "Image",
                "config": {
                  "label": "image",
                  "constraint": {},
                  "thumbnails": []
                }
              }
            }
          }
        },
        "button": {
          "type": "Link",
          "config": {
            "label": "button",
            "placeholder": "",
            "select": null,
            "allowTargetBlank": true,
            "allowText": true,
            "repeat": false
          }
        }
      },
      "items": {}
    },
    {
      "id": "video",
      "name": "video",
      "docURL": "...",
      "version": "initial",
      "description": "Default",
      "imageUrl": "",
      "primary": {
        "title": {
          "type": "Text",
          "config": {
            "label": "title",
            "placeholder": ""
          }
        },
        "subtitle": {
          "type": "Text",
          "config": {
            "label": "subtitle",
            "placeholder": ""
          }
        },
        "video": {
          "type": "Link",
          "config": {
            "label": "video",
            "placeholder": "",
            "select": "media",
            "allowText": true
          }
        }
      },
      "items": {}
    },
    {
      "id": "internal",
      "name": "internal",
      "docURL": "...",
      "version": "initial",
      "description": "Default",
      "imageUrl": "",
      "primary": {},
      "items": {}
    }
  ]
}